LICENSE.txt
MANIFEST.in
README.md
pyproject.toml
setup.cfg
setup.py
versioneer.py
xyRemovebg/__init__.py
xyRemovebg/_version.py
xyRemovebg/bg.py
xyRemovebg/cli.py
xyRemovebg/detect.py
xyRemovebg.egg-info/PKG-INFO
xyRemovebg.egg-info/SOURCES.txt
xyRemovebg.egg-info/dependency_links.txt
xyRemovebg.egg-info/entry_points.txt
xyRemovebg.egg-info/requires.txt
xyRemovebg.egg-info/top_level.txt