Metadata-Version: 2.1
Name: xyRemovebg
Version: 1.0.1
Summary: Remove image background
Home-page: UNKNOWN
Author: chenmingkang
Author-email: chenmingkang@qq.com
License: UNKNOWN
Keywords: asassasasaasas
Platform: UNKNOWN
Classifier: License :: OSI Approved :: MIT License
Classifier: Programming Language :: Python :: 3 :: Only
Requires-Python: >=3.8, <4
Provides-Extra: gpu
